[{"id":"20eeaf41372f7b17","type":"tab","label":"[inject] repeat interval","disabled":false,"info":"Ensure that the repeat functionality of the inject node is working.\n","env":[{"name":"ERED_TIMEOUT","value":"5","type":"num"},{"name":"ERED_NOT_EUNIT","value":"true","type":"bool"}]},{"id":"bf343c186aae3902","type":"inject","z":"20eeaf41372f7b17","name":"","props":[{"p":"payload"}],"repeat":"1","crontab":"","once":false,"onceDelay":"0.5","topic":"","payload":"","payloadType":"date","x":714,"y":597,"wires":[["1491364b8fe993d5"]]},{"id":"1491364b8fe993d5","type":"ut-assert-success","z":"20eeaf41372f7b17","name":"","count":"5","x":949,"y":733,"wires":[]}]