[{"disabled":false,"env":[],"id":"07452607645aeeb7","info":"Ensure that the corrent format type is set for the results of the JSONata expression.","label":"[debug] type hadling of JSONata reslults","type":"tab"},{"h":278,"id":"bffb78cb1ac976a2","name":"appending hash/map to string does not work in JSONata","nodes":["2bea31d3828bc60c","340a0798b871641f","b2f66cf4694a1f60","26cca2c2fb5c36aa","415733697ed0abbf","f2979b9a3d787354"],"style":{"label":true},"type":"group","w":751,"x":85,"y":806,"z":"07452607645aeeb7"},{"h":301,"id":"fbed45b6963bab39","name":"always string because JSONata converts to string","nodes":["9a574c543df17059","05aa6a4218f4e846","ffd75ed0d76ac539","a541e66eca84817d","b75a71a46914f437","384b559b03a12628","4ebbcaa7ee91744f"],"style":{"label":true},"type":"group","w":724,"x":92,"y":479,"z":"07452607645aeeb7"},{"crontab":"","g":"fbed45b6963bab39","id":"9a574c543df17059","name":"","once":false,"onceDelay":0.1,"payload":"252457650000","payloadType":"num","props":[{"p":"payload"},{"p":"topic","vt":"str"}],"repeat":"","topic":"","type":"inject","wires":[["05aa6a4218f4e846"]],"x":222,"y":520,"z":"07452607645aeeb7"},{"active":true,"complete":"$toString($$.payload & \"apart\")","console":false,"g":"fbed45b6963bab39","id":"05aa6a4218f4e846","name":"debug 1","statusType":"auto","statusVal":"","targetType":"jsonata","tosidebar":true,"tostatus":false,"type":"debug","wires":[],"x":485,"y":520,"z":"07452607645aeeb7"},{"crontab":"","g":"fbed45b6963bab39","id":"ffd75ed0d76ac539","name":"","once":false,"onceDelay":0.1,"payload":"[1,2,3,4,5]","payloadType":"json","props":[{"p":"payload"},{"p":"topic","vt":"str"}],"repeat":"","topic":"","type":"inject","wires":[["05aa6a4218f4e846"]],"x":202,"y":604.5,"z":"07452607645aeeb7"},{"crontab":"","g":"fbed45b6963bab39","id":"a541e66eca84817d","name":"","once":false,"onceDelay":0.1,"payload":"\"ddd\"","payloadType":"json","props":[{"p":"payload"},{"p":"topic","vt":"str"}],"repeat":"","topic":"","type":"inject","wires":[["05aa6a4218f4e846"]],"x":192,"y":688,"z":"07452607645aeeb7"},{"g":"fbed45b6963bab39","id":"b75a71a46914f437","inverse":false,"msgtype":"normal","name":"","nodeid":"05aa6a4218f4e846","scope":["05aa6a4218f4e846"],"type":"ut-assert-debug","wires":[["384b559b03a12628"]],"x":561,"y":614,"z":"07452607645aeeb7"},{"crontab":"","id":"5f7b2ae4244160d3","name":"","once":false,"onceDelay":0.1,"payload":"252457650000","payloadType":"num","props":[{"p":"payload"},{"p":"topic","vt":"str"}],"repeat":"","topic":"","type":"inject","wires":[["f3a0419d04ed4222"]],"x":1087,"y":189,"z":"07452607645aeeb7"},{"active":true,"complete":"$$.payload","console":false,"id":"f3a0419d04ed4222","name":"debug 4","statusType":"auto","statusVal":"","targetType":"jsonata","tosidebar":true,"tostatus":false,"type":"debug","wires":[],"x":1070,"y":237,"z":"07452607645aeeb7"},{"id":"5d63579344ca7e87","inverse":false,"msgtype":"normal","name":"","nodeid":"f3a0419d04ed4222","scope":["f3a0419d04ed4222"],"type":"ut-assert-debug","wires":[["a035f292b851a76e"]],"x":1151,"y":293,"z":"07452607645aeeb7"},{"active":true,"complete":"$toString($$.payload & \"apart\")","console":false,"g":"bffb78cb1ac976a2","id":"2bea31d3828bc60c","name":"debug 6","statusType":"auto","statusVal":"","targetType":"jsonata","tosidebar":true,"tostatus":false,"type":"debug","wires":[],"x":256,"y":916.25,"z":"07452607645aeeb7"},{"crontab":"","g":"bffb78cb1ac976a2","id":"340a0798b871641f","name":"","once":false,"onceDelay":0.1,"payload":"{\"d\":\"d\"}","payloadType":"json","props":[{"p":"payload"},{"p":"topic","vt":"str"}],"repeat":"","topic":"","type":"inject","wires":[["2bea31d3828bc60c"]],"x":191,"y":847,"z":"07452607645aeeb7"},{"g":"bffb78cb1ac976a2","id":"b2f66cf4694a1f60","name":"","scope":["2bea31d3828bc60c"],"type":"catch","uncaught":false,"wires":[["26cca2c2fb5c36aa"]],"x":318,"y":985.5,"z":"07452607645aeeb7"},{"g":"bffb78cb1ac976a2","id":"26cca2c2fb5c36aa","name":"","type":"ut-assert-failure","wires":[],"x":598,"y":985.5,"z":"07452607645aeeb7"},{"g":"bffb78cb1ac976a2","id":"415733697ed0abbf","inverse":false,"msgtype":"normal","name":"","nodeid":"2bea31d3828bc60c","scope":["2bea31d3828bc60c"],"type":"ut-assert-debug","wires":[["f2979b9a3d787354"]],"x":418,"y":1043,"z":"07452607645aeeb7"},{"g":"bffb78cb1ac976a2","id":"f2979b9a3d787354","ignore_failure_if_succeed":false,"name":"","rules":[{"p":"payload.msg","pt":"msg","t":"eql","to":"Invalid JSONata expression: badarg (<<\"$toString($$.payload & \\\"apart\\\")\">>)","tot":"str"}],"type":"ut-assert-values","wires":[[]],"x":700,"y":1043,"z":"07452607645aeeb7"},{"g":"fbed45b6963bab39","id":"384b559b03a12628","ignore_failure_if_succeed":false,"name":"","rules":[{"p":"payload.format","pt":"msg","t":"eql","to":"string","tot":"str"}],"type":"ut-assert-values","wires":[[]],"x":680,"y":736,"z":"07452607645aeeb7"},{"crontab":"","g":"fbed45b6963bab39","id":"4ebbcaa7ee91744f","name":"","once":false,"onceDelay":0.1,"payload":"1.123","payloadType":"num","props":[{"p":"payload"},{"p":"topic","vt":"str"}],"repeat":"","topic":"","type":"inject","wires":[["05aa6a4218f4e846"]],"x":188,"y":739,"z":"07452607645aeeb7"},{"active":true,"complete":"$$.payload","console":false,"id":"6b1554f4f74b1805","name":"debug 3","statusType":"auto","statusVal":"","targetType":"jsonata","tosidebar":true,"tostatus":false,"type":"debug","wires":[],"x":1130,"y":455,"z":"07452607645aeeb7"},{"crontab":"","id":"c437d84fbae30b7c","name":"","once":false,"onceDelay":0.1,"payload":"{\"d\":\"d\"}","payloadType":"json","props":[{"p":"payload"},{"p":"topic","vt":"str"}],"repeat":"","topic":"","type":"inject","wires":[["6b1554f4f74b1805"]],"x":1080,"y":404,"z":"07452607645aeeb7"},{"id":"b514b39670fd62d6","inverse":false,"msgtype":"normal","name":"","nodeid":"6b1554f4f74b1805","scope":["6b1554f4f74b1805"],"type":"ut-assert-debug","wires":[["a6e2ccd2e332dbcd"]],"x":1210,"y":522,"z":"07452607645aeeb7"},{"active":true,"complete":"$$.payload","console":false,"id":"6dd0d2a212c62666","name":"debug 7","statusType":"auto","statusVal":"","targetType":"jsonata","tosidebar":true,"tostatus":false,"type":"debug","wires":[],"x":1139,"y":679,"z":"07452607645aeeb7"},{"crontab":"","id":"0e952db2b13797ba","name":"","once":false,"onceDelay":0.1,"payload":"[1,2,3,4,5]","payloadType":"json","props":[{"p":"payload"},{"p":"topic","vt":"str"}],"repeat":"","topic":"","type":"inject","wires":[["6dd0d2a212c62666"]],"x":1083,"y":630,"z":"07452607645aeeb7"},{"id":"8dbb1864d191a8bd","inverse":false,"msgtype":"normal","name":"","nodeid":"6dd0d2a212c62666","scope":["6dd0d2a212c62666"],"type":"ut-assert-debug","wires":[["ab9c55e84b9f6c15"]],"x":1219,"y":738,"z":"07452607645aeeb7"},{"active":true,"complete":"$$.payload","console":false,"id":"aabf09218c1ae0d4","name":"debug 9","statusType":"auto","statusVal":"","targetType":"jsonata","tosidebar":true,"tostatus":false,"type":"debug","wires":[],"x":1144,"y":918,"z":"07452607645aeeb7"},{"crontab":"","id":"b0dfd8b253bc035b","name":"","once":false,"onceDelay":0.1,"payload":"\"ddd\"","payloadType":"json","props":[{"p":"payload"},{"p":"topic","vt":"str"}],"repeat":"","topic":"","type":"inject","wires":[["aabf09218c1ae0d4"]],"x":1075,"y":870,"z":"07452607645aeeb7"},{"id":"9ea41437d97547bc","inverse":false,"msgtype":"normal","name":"","nodeid":"aabf09218c1ae0d4","scope":["aabf09218c1ae0d4"],"type":"ut-assert-debug","wires":[["a3595ef7f66f5a4a"]],"x":1224,"y":987,"z":"07452607645aeeb7"},{"id":"a035f292b851a76e","ignore_failure_if_succeed":false,"name":"","rules":[{"p":"payload.format","pt":"msg","t":"eql","to":"number","tot":"str"}],"type":"ut-assert-values","wires":[[]],"x":1507,"y":293,"z":"07452607645aeeb7"},{"id":"a6e2ccd2e332dbcd","ignore_failure_if_succeed":false,"name":"","rules":[{"p":"payload.format","pt":"msg","t":"eql","to":"Object","tot":"str"}],"type":"ut-assert-values","wires":[[]],"x":1507,"y":522,"z":"07452607645aeeb7"},{"id":"ab9c55e84b9f6c15","ignore_failure_if_succeed":false,"name":"","rules":[{"p":"payload.format","pt":"msg","t":"eql","to":"array","tot":"str"}],"type":"ut-assert-values","wires":[[]],"x":1507,"y":738,"z":"07452607645aeeb7"},{"id":"a3595ef7f66f5a4a","ignore_failure_if_succeed":false,"name":"","rules":[{"p":"payload.format","pt":"msg","t":"eql","to":"string","tot":"str"}],"type":"ut-assert-values","wires":[[]],"x":1507,"y":930,"z":"07452607645aeeb7"}]