[{"disabled":false,"env":[],"id":"1db9c9a1b92e0263","info":"Ensure that if no command is found, that an exception is raised.","label":"[exec] empty commands are not supported","type":"tab"},{"h":447,"id":"8990d3a87c1d88e9","name":"exception is captured no debug message from the exec node","nodes":["978368148e7f6eb4","959ec1c26c0b5a71","4f562ce43ed17d54","2e0dbb434960a174","106a2767f80ae733","659c7d4eabd482f7","c3fc3205048f92a5","81c5fc69c7d37db7","f2da3949fee8dd1f"],"style":{"label":true},"type":"group","w":732,"x":120,"y":741.5,"z":"1db9c9a1b92e0263"},{"h":276.5,"id":"fa5e911e93d67c66","name":"exception isn't captured so the exec node generates a debug message","nodes":["72554cc55499d2ea","911478bf42eac2a7","e618fb7931bb3359","9eb18b85e9ee1966","59850e7a4c42a9d7","3d01a5a74bb07b13","45f10d88798fb588"],"style":{"label":true},"type":"group","w":936,"x":156,"y":271.5,"z":"1db9c9a1b92e0263"},{"crontab":"","g":"fa5e911e93d67c66","id":"72554cc55499d2ea","name":"","once":false,"onceDelay":0.1,"payload":"","payloadType":"date","props":[{"p":"payload"},{"p":"topic","vt":"str"}],"repeat":"","topic":"","type":"inject","wires":[["911478bf42eac2a7"]],"x":262,"y":318,"z":"1db9c9a1b92e0263"},{"addpay":"","append":"","command":"","g":"fa5e911e93d67c66","id":"911478bf42eac2a7","name":"","oldrc":false,"timer":"","type":"exec","useSpawn":"true","winHide":false,"wires":[["e618fb7931bb3359"],["9eb18b85e9ee1966"],["59850e7a4c42a9d7"]],"x":525,"y":439,"z":"1db9c9a1b92e0263"},{"g":"fa5e911e93d67c66","id":"e618fb7931bb3359","name":"","type":"ut-assert-failure","wires":[],"x":715,"y":375.5,"z":"1db9c9a1b92e0263"},{"g":"fa5e911e93d67c66","id":"9eb18b85e9ee1966","name":"","type":"ut-assert-failure","wires":[],"x":715,"y":439,"z":"1db9c9a1b92e0263"},{"g":"fa5e911e93d67c66","id":"59850e7a4c42a9d7","name":"","type":"ut-assert-failure","wires":[],"x":715,"y":507,"z":"1db9c9a1b92e0263"},{"g":"fa5e911e93d67c66","id":"3d01a5a74bb07b13","inverse":false,"msgtype":"error","name":"","nodeid":"911478bf42eac2a7","scope":["911478bf42eac2a7"],"type":"ut-assert-debug","wires":[["45f10d88798fb588"]],"x":591,"y":312.5,"z":"1db9c9a1b92e0263"},{"crontab":"","g":"8990d3a87c1d88e9","id":"978368148e7f6eb4","name":"","once":false,"onceDelay":0.1,"payload":"","payloadType":"date","props":[{"p":"payload"},{"p":"topic","vt":"str"}],"repeat":"","topic":"","type":"inject","wires":[["959ec1c26c0b5a71"]],"x":226,"y":814,"z":"1db9c9a1b92e0263"},{"addpay":"","append":"","command":"","g":"8990d3a87c1d88e9","id":"959ec1c26c0b5a71","name":"","oldrc":false,"timer":"","type":"exec","useSpawn":"true","winHide":false,"wires":[["4f562ce43ed17d54"],["2e0dbb434960a174"],["106a2767f80ae733"]],"x":469,"y":911,"z":"1db9c9a1b92e0263"},{"g":"8990d3a87c1d88e9","id":"4f562ce43ed17d54","name":"","type":"ut-assert-failure","wires":[],"x":659,"y":847.5,"z":"1db9c9a1b92e0263"},{"g":"8990d3a87c1d88e9","id":"2e0dbb434960a174","name":"","type":"ut-assert-failure","wires":[],"x":659,"y":911,"z":"1db9c9a1b92e0263"},{"g":"8990d3a87c1d88e9","id":"106a2767f80ae733","name":"","type":"ut-assert-failure","wires":[],"x":659,"y":979,"z":"1db9c9a1b92e0263"},{"g":"8990d3a87c1d88e9","id":"659c7d4eabd482f7","inverse":true,"msgtype":"error","name":"","nodeid":"959ec1c26c0b5a71","scope":["959ec1c26c0b5a71"],"type":"ut-assert-debug","wires":[[]],"x":536,"y":782.5,"z":"1db9c9a1b92e0263"},{"g":"8990d3a87c1d88e9","id":"c3fc3205048f92a5","name":"","scope":["959ec1c26c0b5a71"],"type":"catch","uncaught":false,"wires":[["81c5fc69c7d37db7","f2da3949fee8dd1f"]],"x":484,"y":1089.75,"z":"1db9c9a1b92e0263"},{"count":1,"g":"8990d3a87c1d88e9","id":"81c5fc69c7d37db7","name":"","type":"ut-assert-success","wires":[],"x":746,"y":1089.75,"z":"1db9c9a1b92e0263"},{"g":"8990d3a87c1d88e9","id":"f2da3949fee8dd1f","ignore_failure_if_succeed":false,"name":"","rules":[{"p":"error.message","pt":"msg","t":"eql","to":"TypeError: The argument 'command' cannot be empty. Received ''","tot":"str"}],"type":"ut-assert-values","wires":[[]],"x":716,"y":1147.5,"z":"1db9c9a1b92e0263"},{"g":"fa5e911e93d67c66","id":"45f10d88798fb588","ignore_failure_if_succeed":false,"name":"","rules":[{"p":"payload['level']","pt":"msg","t":"eql","to":"20","tot":"num"},{"p":"payload.format","pt":"msg","t":"eql","to":"object","tot":"str"},{"p":"payload.msg.error_msg","pt":"msg","t":"eql","to":"TypeError: The argument 'command' cannot be empty. Received ''","tot":"str"},{"p":"payload.id","pt":"msg","t":"eql","to":"911478bf42eac2a7","tot":"str"}],"type":"ut-assert-values","wires":[[]],"x":986,"y":441,"z":"1db9c9a1b92e0263"}]